safeword/__init__.py
safeword/safeword.py
safeword/resources/wordlist.csv
safeword/resources/wordlist.json
safeword/tests/__init__.py
safeword-0.1.1.dist-info/LICENSE
safeword-0.1.1.dist-info/METADATA
safeword-0.1.1.dist-info/WHEEL
safeword-0.1.1.dist-info/top_level.txt
safeword-0.1.1.dist-info/RECORD
