Metadata-Version: 2.1
Name: safeword
Version: 0.1.1
Summary: A small utility for generating character slugs on demand.
Home-page: https://github.com/e-ht/safeword
Author: eht
Author-email: jared@e.ht
License: Unlicense
Platform: UNKNOWN
Classifier: Development Status :: 2 - Pre-Alpha
Classifier: Programming Language :: Python :: 3
Classifier: Operating System :: POSIX :: Linux
Classifier: License :: Public Domain
